[
    {
        "subDomain":"a55"
    },
    {
        "subDomain":"a55hole"
    },
    {
        "subDomain":"ahole"
    },
    {
        "subDomain":"anal"
    },
    {
        "subDomain":"aeolus"
    },
    {
        "subDomain":"analprobe"
    },
    {
        "subDomain":"anus"
    },
    {
        "subDomain":"areola"
    },
    {
        "subDomain":"areole"
    },
    {
        "subDomain":"arian"
    },
    {
        "subDomain":"aryan"
    },
    {
        "subDomain":"ass"
    },
    {
        "subDomain":"anilingus"
    },
    {
        "subDomain":"assbang"
    },
    {
        "subDomain":"assbangs"
    },
    {
        "subDomain":"assbanged"
    },
    {
        "subDomain":"assfuck"
    },
    {
        "subDomain":"assfucker"
    },
    {
        "subDomain":"assh0le"
    },
    {
        "subDomain":"asshat"
    },
    {
        "subDomain":"asses"
    },
    {
        "subDomain":"assholes"
    },
    {
        "subDomain":"assho1e"
    },
    {
        "subDomain":"assmaster"
    },
    {
        "subDomain":"assmunch"
    },
    {
        "subDomain":"asswipe"
    },
    {
        "subDomain":"asswipes"
    },
    {
        "subDomain":"azazel"
    },
    {
        "subDomain":"ass hole"
    },
    {
        "subDomain":"babe"
    },
    {
        "subDomain":"babes"
    },
    {
        "subDomain":"ballsack"
    },
    {
        "subDomain":"azz"
    },
    {
        "subDomain":"banger"
    },
    {
        "subDomain":"barf"
    },
    {
        "subDomain":"bastard"
    },
    {
        "subDomain":"bastards"
    },
    {
        "subDomain":"bawdy"
    },
    {
        "subDomain":"bang"
    },
    {
        "subDomain":"b1tch"
    },
    {
        "subDomain":"beastiality"
    },
    {
        "subDomain":"beater"
    },
    {
        "subDomain":"beaver"
    },
    {
        "subDomain":"beer"
    },
    {
        "subDomain":"beeyotch"
    },
    {
        "subDomain":"beaner"
    },
    {
        "subDomain":"beardedclam"
    },
    {
        "subDomain":"bigtits"
    },
    {
        "subDomain":"beatch"
    },
    {
        "subDomain":"big tits"
    },
    {
        "subDomain":"bimbo"
    },
    {
        "subDomain":"bitch"
    },
    {
        "subDomain":"bitched"
    },
    {
        "subDomain":"biatch"
    },
    {
        "subDomain":"beotch"
    },
    {
        "subDomain":"bitches"
    },
    {
        "subDomain":"blowjob"
    },
    {
        "subDomain":"blowjobs"
    },
    {
        "subDomain":"bod"
    },
    {
        "subDomain":"bodily"
    },
    {
        "subDomain":"boink"
    },
    {
        "subDomain":"bollock"
    },
    {
        "subDomain":"bollocks"
    },
    {
        "subDomain":"blow job"
    },
    {
        "subDomain":"bollok"
    },
    {
        "subDomain":"bone"
    },
    {
        "subDomain":"boned"
    },
    {
        "subDomain":"boner"
    },
    {
        "subDomain":"boners"
    },
    {
        "subDomain":"bitchy"
    },
    {
        "subDomain":"boobies"
    },
    {
        "subDomain":"boob"
    },
    {
        "subDomain":"boobs"
    },
    {
        "subDomain":"booger"
    },
    {
        "subDomain":"bookie"
    },
    {
        "subDomain":"booby"
    },
    {
        "subDomain":"bootee"
    },
    {
        "subDomain":"bong"
    },
    {
        "subDomain":"blow"
    },
    {
        "subDomain":"booty"
    },
    {
        "subDomain":"boozy"
    },
    {
        "subDomain":"boozer"
    },
    {
        "subDomain":"bosomy"
    },
    {
        "subDomain":"bosom"
    },
    {
        "subDomain":"bowels"
    },
    {
        "subDomain":"bowel"
    },
    {
        "subDomain":"brassiere"
    },
    {
        "subDomain":"bra"
    },
    {
        "subDomain":"breast"
    },
    {
        "subDomain":"breasts"
    },
    {
        "subDomain":"bugger"
    },
    {
        "subDomain":"bukkake"
    },
    {
        "subDomain":"bootie"
    },
    {
        "subDomain":"booze"
    },
    {
        "subDomain":"bullshitted"
    },
    {
        "subDomain":"bull shit"
    },
    {
        "subDomain":"bung"
    },
    {
        "subDomain":"bullshits"
    },
    {
        "subDomain":"bullturds"
    },
    {
        "subDomain":"butt"
    },
    {
        "subDomain":"busty"
    },
    {
        "subDomain":"butt fuck"
    },
    {
        "subDomain":"buttfucker"
    },
    {
        "subDomain":"buttfuck"
    },
    {
        "subDomain":"buttplug"
    },
    {
        "subDomain":"c.0.c.k"
    },
    {
        "subDomain":"c.o.c.k."
    },
    {
        "subDomain":"c0ck"
    },
    {
        "subDomain":"c.u.n.t"
    },
    {
        "subDomain":"caca"
    },
    {
        "subDomain":"c-0-c-k"
    },
    {
        "subDomain":"cahone"
    },
    {
        "subDomain":"cameltoe"
    },
    {
        "subDomain":"carpetmuncher"
    },
    {
        "subDomain":"cervix"
    },
    {
        "subDomain":"cawk"
    },
    {
        "subDomain":"chinc"
    },
    {
        "subDomain":"chincs"
    },
    {
        "subDomain":"chink"
    },
    {
        "subDomain":"chink"
    },
    {
        "subDomain":"chode"
    },
    {
        "subDomain":"chodes"
    },
    {
        "subDomain":"cl1t"
    },
    {
        "subDomain":"buttfucker"
    },
    {
        "subDomain":"climax"
    },
    {
        "subDomain":"clitoris"
    },
    {
        "subDomain":"clits"
    },
    {
        "subDomain":"clitty"
    },
    {
        "subDomain":"clitorus"
    },
    {
        "subDomain":"clit"
    },
    {
        "subDomain":"cocaine"
    },
    {
        "subDomain":"cocain"
    },
    {
        "subDomain":"cockblock"
    },
    {
        "subDomain":"c-o-c-k"
    },
    {
        "subDomain":"cockholster"
    },
    {
        "subDomain":"cockknocker"
    },
    {
        "subDomain":"cocks"
    },
    {
        "subDomain":"cocksmoker"
    },
    {
        "subDomain":"cocksucker"
    },
    {
        "subDomain":"cock"
    },
    {
        "subDomain":"cock sucker"
    },
    {
        "subDomain":"coital"
    },
    {
        "subDomain":"condom"
    },
    {
        "subDomain":"coon"
    },
    {
        "subDomain":"coons"
    },
    {
        "subDomain":"crabs"
    },
    {
        "subDomain":"commie"
    },
    {
        "subDomain":"corksucker"
    },
    {
        "subDomain":"crackwhore"
    },
    {
        "subDomain":"cracker"
    },
    {
        "subDomain":"crack"
    },
    {
        "subDomain":"crap"
    },
    {
        "subDomain":"crappy"
    },
    {
        "subDomain":"cum"
    },
    {
        "subDomain":"cumming"
    },
    {
        "subDomain":"cummin"
    },
    {
        "subDomain":"cumslut"
    },
    {
        "subDomain":"cumstain"
    },
    {
        "subDomain":"cunilingus"
    },
    {
        "subDomain":"cunnilingus"
    },
    {
        "subDomain":"cunny"
    },
    {
        "subDomain":"cunt"
    },
    {
        "subDomain":"cumshots"
    },
    {
        "subDomain":"cumshot"
    },
    {
        "subDomain":"cuntface"
    },
    {
        "subDomain":"cunt"
    },
    {
        "subDomain":"c-u-n-t"
    },
    {
        "subDomain":"cunthunter"
    },
    {
        "subDomain":"cunts"
    },
    {
        "subDomain":"cuntlicker"
    },
    {
        "subDomain":"cuntlick"
    },
    {
        "subDomain":"d0ng"
    },
    {
        "subDomain":"d1ck"
    },
    {
        "subDomain":"d0uch3"
    },
    {
        "subDomain":"d0uche"
    },
    {
        "subDomain":"d1ld0"
    },
    {
        "subDomain":"d1ldo"
    },
    {
        "subDomain":"dammit"
    },
    {
        "subDomain":"dago"
    },
    {
        "subDomain":"damn"
    },
    {
        "subDomain":"damned"
    },
    {
        "subDomain":"damnit"
    },
    {
        "subDomain":"dawgie-style"
    },
    {
        "subDomain":"dick"
    },
    {
        "subDomain":"dagos"
    },
    {
        "subDomain":"dickface"
    },
    {
        "subDomain":"dickflipper"
    },
    {
        "subDomain":"dickbag"
    },
    {
        "subDomain":"dickdipper"
    },
    {
        "subDomain":"dickheads"
    },
    {
        "subDomain":"dickhead"
    },
    {
        "subDomain":"dick-ish"
    },
    {
        "subDomain":"dickripper"
    },
    {
        "subDomain":"dickweed"
    },
    {
        "subDomain":"dickish"
    },
    {
        "subDomain":"dickzipper"
    },
    {
        "subDomain":"dicksipper"
    },
    {
        "subDomain":"dike"
    },
    {
        "subDomain":"dickwhipper"
    },
    {
        "subDomain":"diddle"
    },
    {
        "subDomain":"dildo"
    },
    {
        "subDomain":"dildos"
    },
    {
        "subDomain":"diligaf"
    },
    {
        "subDomain":"bullshit"
    },
    {
        "subDomain":"dillweed"
    },
    {
        "subDomain":"dipship"
    },
    {
        "subDomain":"dingle"
    },
    {
        "subDomain":"doggie-style"
    },
    {
        "subDomain":"doggy-style"
    },
    {
        "subDomain":"dong"
    },
    {
        "subDomain":"doofus"
    },
    {
        "subDomain":"dimwit"
    },
    {
        "subDomain":"doosh"
    },
    {
        "subDomain":"douchebag"
    },
    {
        "subDomain":"dopey"
    },
    {
        "subDomain":"douchebags"
    },
    {
        "subDomain":"douchey"
    },
    {
        "subDomain":"drunk"
    },
    {
        "subDomain":"dumbass"
    },
    {
        "subDomain":"dumass"
    },
    {
        "subDomain":"dummy"
    },
    {
        "subDomain":"douch3"
    },
    {
        "subDomain":"dyke"
    },
    {
        "subDomain":"dykes"
    },
    {
        "subDomain":"ejaculate"
    },
    {
        "subDomain":"dumbasses"
    },
    {
        "subDomain":"erection"
    },
    {
        "subDomain":"erotic"
    },
    {
        "subDomain":"essohbee"
    },
    {
        "subDomain":"extacy"
    },
    {
        "subDomain":"enlargement"
    },
    {
        "subDomain":"extasy"
    },
    {
        "subDomain":"f.u.c.k"
    },
    {
        "subDomain":"erect"
    },
    {
        "subDomain":"fagg"
    },
    {
        "subDomain":"fag"
    },
    {
        "subDomain":"fagged"
    },
    {
        "subDomain":"faggit"
    },
    {
        "subDomain":"fagot"
    },
    {
        "subDomain":"fack"
    },
    {
        "subDomain":"faggot"
    },
    {
        "subDomain":"faigt"
    },
    {
        "subDomain":"fannybandit"
    },
    {
        "subDomain":"fart"
    },
    {
        "subDomain":"fags"
    },
    {
        "subDomain":"fartknocker"
    },
    {
        "subDomain":"faig"
    },
    {
        "subDomain":"felch"
    },
    {
        "subDomain":"fat"
    },
    {
        "subDomain":"felching"
    },
    {
        "subDomain":"fellate"
    },
    {
        "subDomain":"fellatio"
    },
    {
        "subDomain":"feltch"
    },
    {
        "subDomain":"fisted"
    },
    {
        "subDomain":"feltcher"
    },
    {
        "subDomain":"felcher"
    },
    {
        "subDomain":"fisting"
    },
    {
        "subDomain":"fisty"
    },
    {
        "subDomain":"floozy"
    },
    {
        "subDomain":"foad"
    },
    {
        "subDomain":"foreskin"
    },
    {
        "subDomain":"fondle"
    },
    {
        "subDomain":"foobar"
    },
    {
        "subDomain":"freex"
    },
    {
        "subDomain":"douche"
    },
    {
        "subDomain":"fuck"
    },
    {
        "subDomain":"f-u-c-k"
    },
    {
        "subDomain":"fuckass"
    },
    {
        "subDomain":"fucked"
    },
    {
        "subDomain":"fucked"
    },
    {
        "subDomain":"fucker"
    },
    {
        "subDomain":"fuckface"
    },
    {
        "subDomain":"frigga"
    },
    {
        "subDomain":"fuckin"
    },
    {
        "subDomain":"fucking"
    },
    {
        "subDomain":"fucknugget"
    },
    {
        "subDomain":"fubar"
    },
    {
        "subDomain":"fuckoff"
    },
    {
        "subDomain":"frigg"
    },
    {
        "subDomain":"fucktard"
    },
    {
        "subDomain":"fucknut"
    },
    {
        "subDomain":"fuckup"
    },
    {
        "subDomain":"fuckwad"
    },
    {
        "subDomain":"fuckwit"
    },
    {
        "subDomain":"fuck-tard"
    },
    {
        "subDomain":"fucks"
    },
    {
        "subDomain":"fudgepacker"
    },
    {
        "subDomain":"fvck"
    },
    {
        "subDomain":"fuk"
    },
    {
        "subDomain":"fxck"
    },
    {
        "subDomain":"gae"
    },
    {
        "subDomain":"gai"
    },
    {
        "subDomain":"ganja"
    },
    {
        "subDomain":"gays"
    },
    {
        "subDomain":"gey"
    },
    {
        "subDomain":"ghay"
    },
    {
        "subDomain":"ghey"
    },
    {
        "subDomain":"gfy"
    },
    {
        "subDomain":"gigolo"
    },
    {
        "subDomain":"gay"
    },
    {
        "subDomain":"godamn"
    },
    {
        "subDomain":"glans"
    },
    {
        "subDomain":"goddam"
    },
    {
        "subDomain":"goddammit"
    },
    {
        "subDomain":"goddamn"
    },
    {
        "subDomain":"goldenshower"
    },
    {
        "subDomain":"godamnit"
    },
    {
        "subDomain":"goatse"
    },
    {
        "subDomain":"gooks"
    },
    {
        "subDomain":"gringo"
    },
    {
        "subDomain":"gook"
    },
    {
        "subDomain":"gspot"
    },
    {
        "subDomain":"g-spot"
    },
    {
        "subDomain":"guido"
    },
    {
        "subDomain":"gtfo"
    },
    {
        "subDomain":"gonad"
    },
    {
        "subDomain":"gonads"
    },
    {
        "subDomain":"handjob"
    },
    {
        "subDomain":"h0mo"
    },
    {
        "subDomain":"he11"
    },
    {
        "subDomain":"heeb"
    },
    {
        "subDomain":"hell"
    },
    {
        "subDomain":"hebe"
    },
    {
        "subDomain":"hard on"
    },
    {
        "subDomain":"h0m0"
    },
    {
        "subDomain":"hemp"
    },
    {
        "subDomain":"herpes"
    },
    {
        "subDomain":"herpy"
    },
    {
        "subDomain":"hitler"
    },
    {
        "subDomain":"hiv"
    },
    {
        "subDomain":"hobag"
    },
    {
        "subDomain":"hom0"
    },
    {
        "subDomain":"heroin"
    },
    {
        "subDomain":"herp"
    },
    {
        "subDomain":"honky"
    },
    {
        "subDomain":"homoey"
    },
    {
        "subDomain":"hooch"
    },
    {
        "subDomain":"hooker"
    },
    {
        "subDomain":"hoor"
    },
    {
        "subDomain":"hookah"
    },
    {
        "subDomain":"hootch"
    },
    {
        "subDomain":"homey"
    },
    {
        "subDomain":"horny"
    },
    {
        "subDomain":"hump"
    },
    {
        "subDomain":"humped"
    },
    {
        "subDomain":"homo"
    },
    {
        "subDomain":"hooters"
    },
    {
        "subDomain":"humping"
    },
    {
        "subDomain":"hussy"
    },
    {
        "subDomain":"inbred"
    },
    {
        "subDomain":"hymen"
    },
    {
        "subDomain":"j3rk0ff"
    },
    {
        "subDomain":"injun"
    },
    {
        "subDomain":"jackass"
    },
    {
        "subDomain":"incest"
    },
    {
        "subDomain":"jap"
    },
    {
        "subDomain":"jackhole"
    },
    {
        "subDomain":"jackoff"
    },
    {
        "subDomain":"jerk0ff"
    },
    {
        "subDomain":"japs"
    },
    {
        "subDomain":"jerked"
    },
    {
        "subDomain":"jerkoff"
    },
    {
        "subDomain":"hooter"
    },
    {
        "subDomain":"jism"
    },
    {
        "subDomain":"jiz"
    },
    {
        "subDomain":"jizm"
    },
    {
        "subDomain":"jerk"
    },
    {
        "subDomain":"jizz"
    },
    {
        "subDomain":"junky"
    },
    {
        "subDomain":"kike"
    },
    {
        "subDomain":"kikes"
    },
    {
        "subDomain":"junkie"
    },
    {
        "subDomain":"kill"
    },
    {
        "subDomain":"kinky"
    },
    {
        "subDomain":"kkk"
    },
    {
        "subDomain":"jizzed"
    },
    {
        "subDomain":"kooch"
    },
    {
        "subDomain":"klan"
    },
    {
        "subDomain":"kootch"
    },
    {
        "subDomain":"kooches"
    },
    {
        "subDomain":"kyke"
    },
    {
        "subDomain":"kraut"
    },
    {
        "subDomain":"labia"
    },
    {
        "subDomain":"lesbians"
    },
    {
        "subDomain":"knobend"
    },
    {
        "subDomain":"lesbo"
    },
    {
        "subDomain":"lesbos"
    },
    {
        "subDomain":"lez"
    },
    {
        "subDomain":"lech"
    },
    {
        "subDomain":"leper"
    },
    {
        "subDomain":"lezbians"
    },
    {
        "subDomain":"lezbo"
    },
    {
        "subDomain":"lezbian"
    },
    {
        "subDomain":"lezzie"
    },
    {
        "subDomain":"lezzies"
    },
    {
        "subDomain":"lezzy"
    },
    {
        "subDomain":"lmao"
    },
    {
        "subDomain":"loin"
    },
    {
        "subDomain":"lmfao"
    },
    {
        "subDomain":"lezbos"
    },
    {
        "subDomain":"mams"
    },
    {
        "subDomain":"lusty"
    },
    {
        "subDomain":"masterbate"
    },
    {
        "subDomain":"massa"
    },
    {
        "subDomain":"masterbating"
    },
    {
        "subDomain":"masturbate"
    },
    {
        "subDomain":"masterbation"
    },
    {
        "subDomain":"loins"
    },
    {
        "subDomain":"lube"
    },
    {
        "subDomain":"masturbating"
    },
    {
        "subDomain":"menses"
    },
    {
        "subDomain":"menstruate"
    },
    {
        "subDomain":"menstruation"
    },
    {
        "subDomain":"maxi"
    },
    {
        "subDomain":"meth"
    },
    {
        "subDomain":"m-fucking"
    },
    {
        "subDomain":"mofo"
    },
    {
        "subDomain":"masturbation"
    },
    {
        "subDomain":"motherfucka"
    },
    {
        "subDomain":"moron"
    },
    {
        "subDomain":"molest"
    },
    {
        "subDomain":"motherfucker"
    },
    {
        "subDomain":"mtherfucker"
    },
    {
        "subDomain":"mthrfucker"
    },
    {
        "subDomain":"motherfucking"
    },
    {
        "subDomain":"muffdiver"
    },
    {
        "subDomain":"murder"
    },
    {
        "subDomain":"mthrfucking"
    },
    {
        "subDomain":"muthafuckaz"
    },
    {
        "subDomain":"muthafucker"
    },
    {
        "subDomain":"mutherfucking"
    },
    {
        "subDomain":"muthrfucking"
    },
    {
        "subDomain":"nad"
    },
    {
        "subDomain":"mutherfucker"
    },
    {
        "subDomain":"nads"
    },
    {
        "subDomain":"naked"
    },
    {
        "subDomain":"napalm"
    },
    {
        "subDomain":"nappy"
    },
    {
        "subDomain":"muff"
    },
    {
        "subDomain":"negro"
    },
    {
        "subDomain":"nigga"
    },
    {
        "subDomain":"nazism"
    },
    {
        "subDomain":"niggah"
    },
    {
        "subDomain":"niggas"
    },
    {
        "subDomain":"moolie"
    },
    {
        "subDomain":"nigger"
    },
    {
        "subDomain":"niggaz"
    },
    {
        "subDomain":"nazi"
    },
    {
        "subDomain":"niggers"
    },
    {
        "subDomain":"nigger"
    },
    {
        "subDomain":"nimrod"
    },
    {
        "subDomain":"ninny"
    },
    {
        "subDomain":"niglet"
    },
    {
        "subDomain":"nipple"
    },
    {
        "subDomain":"nooky"
    },
    {
        "subDomain":"nympho"
    },
    {
        "subDomain":"niggle"
    },
    {
        "subDomain":"orally"
    },
    {
        "subDomain":"oral"
    },
    {
        "subDomain":"organ"
    },
    {
        "subDomain":"orgasmic"
    },
    {
        "subDomain":"orgies"
    },
    {
        "subDomain":"opiate"
    },
    {
        "subDomain":"orgy"
    },
    {
        "subDomain":"opium"
    },
    {
        "subDomain":"ovary"
    },
    {
        "subDomain":"ovums"
    },
    {
        "subDomain":"p.u.s.s.y."
    },
    {
        "subDomain":"paki"
    },
    {
        "subDomain":"pantie"
    },
    {
        "subDomain":"paddy"
    },
    {
        "subDomain":"panties"
    },
    {
        "subDomain":"ovum"
    },
    {
        "subDomain":"orgasm"
    },
    {
        "subDomain":"pasty"
    },
    {
        "subDomain":"pcp"
    },
    {
        "subDomain":"pedo"
    },
    {
        "subDomain":"pecker"
    },
    {
        "subDomain":"pedophilia"
    },
    {
        "subDomain":"pastie"
    },
    {
        "subDomain":"panty"
    },
    {
        "subDomain":"pedophile"
    },
    {
        "subDomain":"pee"
    },
    {
        "subDomain":"penetration"
    },
    {
        "subDomain":"peepee"
    },
    {
        "subDomain":"penile"
    },
    {
        "subDomain":"pedophiliac"
    },
    {
        "subDomain":"penis"
    },
    {
        "subDomain":"perversion"
    },
    {
        "subDomain":"penial"
    },
    {
        "subDomain":"phallic"
    },
    {
        "subDomain":"phuck"
    },
    {
        "subDomain":"pillowbiter"
    },
    {
        "subDomain":"pimp"
    },
    {
        "subDomain":"peyote"
    },
    {
        "subDomain":"pinko"
    },
    {
        "subDomain":"phalli"
    },
    {
        "subDomain":"piss"
    },
    {
        "subDomain":"piss-off"
    },
    {
        "subDomain":"pms"
    },
    {
        "subDomain":"polack"
    },
    {
        "subDomain":"pissed"
    },
    {
        "subDomain":"pollock"
    },
    {
        "subDomain":"poontang"
    },
    {
        "subDomain":"pissoff"
    },
    {
        "subDomain":"poon"
    },
    {
        "subDomain":"pornography"
    },
    {
        "subDomain":"porno"
    },
    {
        "subDomain":"potty"
    },
    {
        "subDomain":"pot"
    },
    {
        "subDomain":"prig"
    },
    {
        "subDomain":"prostitute"
    },
    {
        "subDomain":"prick"
    },
    {
        "subDomain":"porn"
    },
    {
        "subDomain":"prude"
    },
    {
        "subDomain":"pubis"
    },
    {
        "subDomain":"pubic"
    },
    {
        "subDomain":"punkass"
    },
    {
        "subDomain":"punky"
    },
    {
        "subDomain":"pussies"
    },
    {
        "subDomain":"pube"
    },
    {
        "subDomain":"puss"
    },
    {
        "subDomain":"pussypounder"
    },
    {
        "subDomain":"pussy"
    },
    {
        "subDomain":"puto"
    },
    {
        "subDomain":"queaf"
    },
    {
        "subDomain":"queer"
    },
    {
        "subDomain":"queef"
    },
    {
        "subDomain":"queero"
    },
    {
        "subDomain":"queef"
    },
    {
        "subDomain":"quicky"
    },
    {
        "subDomain":"queers"
    },
    {
        "subDomain":"quim"
    },
    {
        "subDomain":"rape"
    },
    {
        "subDomain":"raper"
    },
    {
        "subDomain":"rapist"
    },
    {
        "subDomain":"racy"
    },
    {
        "subDomain":"raped"
    },
    {
        "subDomain":"rectum"
    },
    {
        "subDomain":"penetrate"
    },
    {
        "subDomain":"reefer"
    },
    {
        "subDomain":"raunch"
    },
    {
        "subDomain":"reetard"
    },
    {
        "subDomain":"rectus"
    },
    {
        "subDomain":"reich"
    },
    {
        "subDomain":"retard"
    },
    {
        "subDomain":"rimjob"
    },
    {
        "subDomain":"rectal"
    },
    {
        "subDomain":"ritard"
    },
    {
        "subDomain":"retarded"
    },
    {
        "subDomain":"r-tard"
    },
    {
        "subDomain":"rump"
    },
    {
        "subDomain":"rtard"
    },
    {
        "subDomain":"ruski"
    },
    {
        "subDomain":"rum"
    },
    {
        "subDomain":"s.h.i.t."
    },
    {
        "subDomain":"revue"
    },
    {
        "subDomain":"s.o.b."
    },
    {
        "subDomain":"s0b"
    },
    {
        "subDomain":"sadist"
    },
    {
        "subDomain":"sadism"
    },
    {
        "subDomain":"scantily"
    },
    {
        "subDomain":"schizo"
    },
    {
        "subDomain":"schlong"
    },
    {
        "subDomain":"screw"
    },
    {
        "subDomain":"screwed"
    },
    {
        "subDomain":"scrog"
    },
    {
        "subDomain":"scrot"
    },
    {
        "subDomain":"scrote"
    },
    {
        "subDomain":"scag"
    },
    {
        "subDomain":"scrud"
    },
    {
        "subDomain":"scum"
    },
    {
        "subDomain":"rumprammer"
    },
    {
        "subDomain":"scrotum"
    },
    {
        "subDomain":"seaman"
    },
    {
        "subDomain":"seamen"
    },
    {
        "subDomain":"seduce"
    },
    {
        "subDomain":"semen"
    },
    {
        "subDomain":"sex"
    },
    {
        "subDomain":"shamedame"
    },
    {
        "subDomain":"s-h-1-t"
    },
    {
        "subDomain":"s-h-i-t"
    },
    {
        "subDomain":"shit"
    },
    {
        "subDomain":"shiteater"
    },
    {
        "subDomain":"shitface"
    },
    {
        "subDomain":"shite"
    },
    {
        "subDomain":"sexual"
    },
    {
        "subDomain":"sh1t"
    },
    {
        "subDomain":"pornhub"
    },
    {
        "subDomain":"test"
    },
    {
        "subDomain":"shithole"
    },
    {
        "subDomain":"testtesttest"
    },
    {
        "subDomain":"goh"
    },
    {
        "subDomain":"an"
    },
    {
        "subDomain":"testtest"
    },
    {
        "subDomain":"shithead"
    },
    {
        "subDomain":"kos"
    },
    {
        "subDomain":"ridam"
    },
    {
        "subDomain":"ridamtoo"
    },
    {
        "subDomain":"lgbt"
    },
    {
        "subDomain":"lesbian"
    },
    {
        "subDomain":"midam"
    },
    {
        "subDomain":"jendeam"
    },
    {
        "subDomain":"koso"
    },
    {
        "subDomain":"kososhare"
    },
    {
        "subDomain":"kososher"
    },
    {
        "subDomain":"ridamto"
    },
    {
        "subDomain":"gay"
    },
    {
        "subDomain":"koon"
    },
    {
        "subDomain":"kooni"
    },
    {
        "subDomain":"koony"
    },
    {
        "subDomain":"keer"
    },
    {
        "subDomain":"kir"
    },
    {
        "subDomain":"koskesh"
    },
    {
        "subDomain":"jakesh"
    },
    {
        "subDomain":"tokhm"
    },
    {
        "subDomain":"tokhmi"
    },
    {
        "subDomain":"sex"
    },
    {
        "subDomain":"madarjende"
    },
    {
        "subDomain":"mamanjende"
    },
    {
        "subDomain":"haroom"
    },
    {
        "subDomain":"kosshare"
    },
    {
        "subDomain":"haroomzade"
    },
    {
        "subDomain":"haroomzadeh"
    },
    {
        "subDomain":"haromzade"
    },
    {
        "subDomain":"kosoo"
    },
    {
        "subDomain":"kosde"
    },
    {
        "subDomain":"kosam"
    },
    {
        "subDomain":"haromzadeh"
    },
    {
        "subDomain":"abtokhm"
    },
    {
        "subDomain":"pashm"
    },
    {
        "subDomain":"pashmam"
    },
    {
        "subDomain":"pashmom"
    },
    {
        "subDomain":"ga"
    },
    {
        "subDomain":"chokhd"
    },
    {
        "subDomain":"sagpedar"
    },
    {
        "subDomain":"pedarsag"
    },
    {
        "subDomain":"loveherfeet"
    },
    {
        "subDomain":"footfetish"
    },
    {
        "subDomain":"haroomzade"
    },
    {
        "subDomain":"shithouse"
    },
    {
        "subDomain":"shitt"
    },
    {
        "subDomain":"shits"
    },
    {
        "subDomain":"shitter"
    },
    {
        "subDomain":"shitty"
    },
    {
        "subDomain":"shitted"
    },
    {
        "subDomain":"shiz"
    },
    {
        "subDomain":"sissy"
    },
    {
        "subDomain":"skag"
    },
    {
        "subDomain":"skank"
    },
    {
        "subDomain":"slave"
    },
    {
        "subDomain":"sleaze"
    },
    {
        "subDomain":"sleazy"
    },
    {
        "subDomain":"slut"
    },
    {
        "subDomain":"slutdumper"
    },
    {
        "subDomain":"sluts"
    },
    {
        "subDomain":"smegma"
    },
    {
        "subDomain":"smut"
    },
    {
        "subDomain":"smutty"
    },
    {
        "subDomain":"slutkiss"
    },
    {
        "subDomain":"sniper"
    },
    {
        "subDomain":"snatch"
    },
    {
        "subDomain":"snuff"
    },
    {
        "subDomain":"s-o-b"
    },
    {
        "subDomain":"souse"
    },
    {
        "subDomain":"soused"
    },
    {
        "subDomain":"sperm"
    },
    {
        "subDomain":"spic"
    },
    {
        "subDomain":"sodom"
    },
    {
        "subDomain":"spick"
    },
    {
        "subDomain":"spik"
    },
    {
        "subDomain":"spiks"
    },
    {
        "subDomain":"spooge"
    },
    {
        "subDomain":"spunk"
    },
    {
        "subDomain":"stfu"
    },
    {
        "subDomain":"stiffy"
    },
    {
        "subDomain":"stoned"
    },
    {
        "subDomain":"strip"
    },
    {
        "subDomain":"stroke"
    },
    {
        "subDomain":"stupid"
    },
    {
        "subDomain":"suck"
    },
    {
        "subDomain":"sucked"
    },
    {
        "subDomain":"sucking"
    },
    {
        "subDomain":"sumofabiatch"
    },
    {
        "subDomain":"t1t"
    },
    {
        "subDomain":"کص"
    },
    {
        "subDomain":"کص کش"
    },
    {
        "subDomain":"masoome"
    },
    {
        "subDomain":"کصو"
    },
    {
        "subDomain":"جنده خونه"
    },
    {
        "subDomain":"کیر"
    },
    {
        "subDomain":"جنده"
    },
    {
        "subDomain":"کصکش"
    },
    {
        "subDomain":"کیری"
    },
    {
        "subDomain":"مادرجنده"
    },
    {
        "subDomain":"مادر جنده"
    },
    {
        "subDomain":"پشمام"
    },
    {
        "subDomain":"tampon"
    },
    {
        "subDomain":"دیلدو"
    },
    {
        "subDomain":"tawdry"
    },
    {
        "subDomain":"tard"
    },
    {
        "subDomain":"teabagging"
    },
    {
        "subDomain":"teat"
    },
    {
        "subDomain":"terd"
    },
    {
        "subDomain":"testee"
    },
    {
        "subDomain":"teste"
    },
    {
        "subDomain":"testicle"
    },
    {
        "subDomain":"testes"
    },
    {
        "subDomain":"thrust"
    },
    {
        "subDomain":"thug"
    },
    {
        "subDomain":"tinkle"
    },
    {
        "subDomain":"tit"
    },
    {
        "subDomain":"titfuck"
    },
    {
        "subDomain":"titi"
    },
    {
        "subDomain":"tits"
    },
    {
        "subDomain":"steamy"
    },
    {
        "subDomain":"titties"
    },
    {
        "subDomain":"titty"
    },
    {
        "subDomain":"tittyfuck"
    },
    {
        "subDomain":"tittiefucker"
    },
    {
        "subDomain":"tittyfucker"
    },
    {
        "subDomain":"toke"
    },
    {
        "subDomain":"toots"
    },
    {
        "subDomain":"tramp"
    },
    {
        "subDomain":"transsexual"
    },
    {
        "subDomain":"trashy"
    },
    {
        "subDomain":"tubgirl"
    },
    {
        "subDomain":"turd"
    },
    {
        "subDomain":"tush"
    },
    {
        "subDomain":"twats"
    },
    {
        "subDomain":"ugly"
    },
    {
        "subDomain":"undies"
    },
    {
        "subDomain":"testis"
    },
    {
        "subDomain":"unwed"
    },
    {
        "subDomain":"urine"
    },
    {
        "subDomain":"urinal"
    },
    {
        "subDomain":"uzi"
    },
    {
        "subDomain":"vag"
    },
    {
        "subDomain":"uterus"
    },
    {
        "subDomain":"vagina"
    },
    {
        "subDomain":"valium"
    },
    {
        "subDomain":"virgin"
    },
    {
        "subDomain":"vixen"
    },
    {
        "subDomain":"viagra"
    },
    {
        "subDomain":"twat"
    },
    {
        "subDomain":"voyeur"
    },
    {
        "subDomain":"vulgar"
    },
    {
        "subDomain":"vulva"
    },
    {
        "subDomain":"wad"
    },
    {
        "subDomain":"wang"
    },
    {
        "subDomain":"vodka"
    },
    {
        "subDomain":"wank"
    },
    {
        "subDomain":"wazoo"
    },
    {
        "subDomain":"wedgie"
    },
    {
        "subDomain":"weed"
    },
    {
        "subDomain":"vomit"
    },
    {
        "subDomain":"weenie"
    },
    {
        "subDomain":"weiner"
    },
    {
        "subDomain":"weewee"
    },
    {
        "subDomain":"weirdo"
    },
    {
        "subDomain":"wench"
    },
    {
        "subDomain":"wh0re"
    },
    {
        "subDomain":"wh0reface"
    },
    {
        "subDomain":"wetback"
    },
    {
        "subDomain":"whitey"
    },
    {
        "subDomain":"wanker"
    },
    {
        "subDomain":"whore"
    },
    {
        "subDomain":"whoralicious"
    },
    {
        "subDomain":"whored"
    },
    {
        "subDomain":"whorealicious"
    },
    {
        "subDomain":"whoreface"
    },
    {
        "subDomain":"whiz"
    },
    {
        "subDomain":"whorehopper"
    },
    {
        "subDomain":"whorehouse"
    },
    {
        "subDomain":"whores"
    },
    {
        "subDomain":"whoring"
    },
    {
        "subDomain":"wigger"
    },
    {
        "subDomain":"wop"
    },
    {
        "subDomain":"wtf"
    },
    {
        "subDomain":"x-rated"
    },
    {
        "subDomain":"xxx"
    },
    {
        "subDomain":"yeasty"
    },
    {
        "subDomain":"yobbo"
    },
    {
        "subDomain":"womb"
    },
    {
        "subDomain":"woody"
    },
    {
        "subDomain":"kossher"
    },
    {
        "subDomain":"zoophile"
    }
]